datallog/__init__.py
datallog/decorators/__init__.py
datallog/decorators/core_step.py
datallog/decorators/step.py
datallog/utils/__init__.py
datallog/utils/cloud_worker.py
datallog/utils/download_selenium_driver.py
datallog/utils/errors.py
datallog/utils/generate_build_file.py
datallog/utils/generate_step_props.py
datallog/utils/get_all_apps.py
datallog/utils/get_step_name_by_index.py
datallog/utils/import_module.py
datallog/utils/selenium.py
datallog/utils/storage.py
datallog/utils/uploader.py
datallog/utils/validate_step_sequence.py
datallog/utils/worker.py
datallog-0.1.34.dist-info/METADATA
datallog-0.1.34.dist-info/WHEEL
datallog-0.1.34.dist-info/RECORD
